LICENSE
MANIFEST.in
README.rst
TEsingle
setup.py
TEsingle.egg-info/PKG-INFO
TEsingle.egg-info/SOURCES.txt
TEsingle.egg-info/dependency_links.txt
TEsingle.egg-info/not-zip-safe
TEsingle.egg-info/requires.txt
TEsingle.egg-info/top_level.txt
TEtools/AlignmentIO.py
TEtools/CellGrapher.py
TEtools/Counters.py
TEtools/EM.py
TEtools/GeneIndex.py
TEtools/TEindex.py