Metadata-Version: 2.1
Name: TEsingle
Version: 1.0
Summary: Tool for estimating differential enrichment of Transposable Elements and other highly repetitive regions in single-cell data
Home-page: https://www.mghlab.org/software/tesingle
Author: Talitha Forcier, Cole Wunderlich, Oliver Tam, Molly Gale Hammell
Author-email: mghcompbio@gmail.com
License: BSD-3-Clause
Keywords: TE transposable element differential enrichment single-cell
Platform: Linux
Classifier: Development Status :: 5 - Production/Stable
Classifier: Intended Audience :: Science/Research
Classifier: Environment :: Console
Classifier: Natural Language :: English
Classifier: License :: OSI Approved :: BSD License
Classifier: Topic :: Scientific/Engineering :: Bio-Informatics
Classifier: Programming Language :: Python :: 3
Classifier: Operating System :: Unix
License-File: LICENSE
